trionesControl/__init__.py
trionesControl/trionesControl.py
trionesControl-1.2.0.dist-info/LICENSE
trionesControl-1.2.0.dist-info/METADATA
trionesControl-1.2.0.dist-info/WHEEL
trionesControl-1.2.0.dist-info/top_level.txt
trionesControl-1.2.0.dist-info/RECORD
