Metadata-Version: 2.1
Name: trionesControl
Version: 1.2.0
Summary: Simple python package to control smart lights using the Triones porotocol
Home-page: https://github.com/Aritzherrero4/python-trionesControl
Author: Aritz Herrero
License: MIT
Platform: UNKNOWN
Classifier: Intended Audience :: Developers
Classifier: Programming Language :: Python :: 3
Classifier: Programming Language :: Python :: 3.7
Classifier: Programming Language :: Python :: 3.8
Classifier: License :: OSI Approved :: MIT License
Classifier: Operating System :: POSIX :: Linux
Requires-Python: >=3.6
Requires-Dist: pexpect
Requires-Dist: pygatt
